whitecapella_cmd/__init__.py
whitecapella_cmd-0.1.1.dist-info/METADATA
whitecapella_cmd-0.1.1.dist-info/WHEEL
whitecapella_cmd-0.1.1.dist-info/entry_points.txt
whitecapella_cmd-0.1.1.dist-info/top_level.txt
whitecapella_cmd-0.1.1.dist-info/RECORD
