Metadata-Version: 2.1
Name: whitecapella_cmd
Version: 0.1.1
Summary: Default template for PDM package
Author-email: whitecapella1 <whitecapella@naver.com>
License: MIT
Requires-Python: >=3.9
Requires-Dist: whitecapella-lotto >=0.2.0
